synth_crunch/__init__.py
synth_crunch/__version__.py
synth_crunch/backtest.py
synth_crunch/baseline.py
synth_crunch/data.py
synth_crunch/interface.py
synth_crunch/test.py
synth_crunch-0.3.1.dist-info/METADATA
synth_crunch-0.3.1.dist-info/WHEEL
synth_crunch-0.3.1.dist-info/top_level.txt
synth_crunch-0.3.1.dist-info/RECORD
