Metadata-Version: 2.4
Name: synth-crunch
Version: 0.3.1
Summary: synth-crunch - Utility package for the Synth competition on CrunchDAO!
Home-page: https://github.com/crunchdao/synth-crunch
Author: Enzo CACERES
Author-email: enzo.caceres@crunchdao.com
Keywords: crunchdao,crunch,synth
Classifier: Intended Audience :: Developers
Classifier: Programming Language :: Python :: 3.10
Requires-Python: >=3.10
Requires-Dist: matplotlib
Requires-Dist: numpy
Requires-Dist: pandas
Requires-Dist: requests
Requires-Dist: tqdm
Requires-Dist: properscoring
Provides-Extra: test
Requires-Dist: parameterized; extra == "test"
Requires-Dist: pytest; extra == "test"
Dynamic: author
Dynamic: author-email
Dynamic: classifier
Dynamic: description
Dynamic: description-content-type
Dynamic: home-page
Dynamic: keywords
Dynamic: provides-extra
Dynamic: requires-dist
Dynamic: requires-python
Dynamic: summary
